{
  "fila_num": 62,
  "url": "https://23fbuscador.rtve.es/document/ocr/1799?page_size=200&page=1",
  "título": "Comisiones militares (10 de marzo de 1982).",
  "páginas": "1",
  "col_3": "",
  "resumen": "La nota informativa señala preocupación por la composición estática de las comisiones militares, cuya cercanía constante con los acusados genera lazos de simpatía que comprometen la objetividad. Se enfatiza la necesidad de modificar su integración, promoviendo una mayor participación de Jefes y Ofic...",
  "palabras_clave": "ARAP/ 10.03.82 notas informativas miembros",
  "transcripcion": "ARAP/ 10.03.82\n\n# NOTA INFORMATIVA\n\nA la vista de las informaciones que llegan, preocupa el comportamiento de los miembros de las diferentes comisiones militares. El que algunas estén formadas por las mismas personas desde que se inició el proceso, es un peligro porque el trato continuo con los inculpados y sus familiares fomenta unos lazos de simpatía difíciles de superar. La necesidad de alterar la composición de las comisiones se ve acrecentada por la conveniencia de que el juicio sea presenciado por el mayor número de Jefes y Oficiales.\n\nDe la 3ª Región Militar - posiblemente la más sensibilizada por estos sucesos - han vuelto a repetir los que vinieron la primera semana, con lo que - dado que la asistencia es voluntaria - se pone de manifiesto una inclinación hacia los procesados que está lejos de la objetividad deseada.\n\nConvendría insistir en este tema y en recordar el comportamiento correcto que deben observar cuantos militares asistan al Consejo de Guerra."
}