{
  "fila_num": 150,
  "url": "https://23fbuscador.rtve.es/document/ocr/1711?page_size=200&page=1",
  "título": "Solicitando datos sobre el Cte. Cortina y equipos de transmisiones (8 de enero de 1982).",
  "páginas": "2",
  "col_3": "",
  "resumen": "El documento consta de dos páginas relacionadas con una investigación sobre la causa 2/81 por Rebelión Militar. La primera página presenta un oficio del Consejo Supremo de Justicia Militar, fechado en 1981, solicitando al mando correspondiente certificaciones acerca de la actividad informativa dia...",
  "palabras_clave": "CONSEJO SUPREMO DE JUSTICIA MILITAR GENERAL CONSEJERO TOGADO INSTRUCTOR CAUSA Nº 2/81",
  "transcripcion": "MICROFILMACION 00471/S\nST / TJ / ME\n3\n\nCONSEJO SUPREMO\nDE JUSTICIA MILITAR\n\nGENERAL CONSEJERO TOGADO\nINSTRUCTOR CAUSA Nº 2/81\n\nILMO. SEÑOR:\n\nNúm. 2\n\nEn cumplimiento de lo acordado en Auto del Consejo Reunido en Sala de Justicia de fecha diecisiete de Noviembre de mil novecientos ochenta y uno dictado en la Causa 2/81 sobre Rebelión Militar, mediante el presente oficio, le intereso que por la autoridad que correspondía de ese Centro, se certifique sobre los siguientes extremos:\n\na) Si en el Organo que mandaba el Comandante CORTINA la actividad informativa diaria de algunos de sus miembros o núcleo de los mismos concluía preceptivamente con la confección y entrega de un informe a sus Jefes.\n\nb) Si en el CESID existe constancia de alguna actividad informativa permanente simultanea con los hechos del veintitrés de febrero y sin ninguna vinculación con ellos.\n\nc) Si la Unidad Escuela, integrada en el Organo que mandaba el Comandante CORTINA, dispone de un sistema de transmisiones independiente del resto, utilizado habitualmente para actividades de enseñanza y no operativas.\n\nd) Si el sistema está integrado por una emisora central fija en las instalaciones, más de tres vehículos con radio teléfonos y otros radio teléfonos portátiles, de los cuales los de tipo medio en funcionamiento no eran más que tres.\n\ne) Si tal sistema de transmisiones no era el más obsoleto, desgastado y de menor rendimiento por lo que se dedicaba a enseñanza.\n\nf) En estas condiciones cual es el alcance medio que cabe esperar en ciudad del radio-teléfono de un vehículo, y cual el del radio-teléfono portátil de tipo medio.\n\nRuego a V.I. la urgente remisión de los certificados.\n\nMICROFILMACION 00471/S\n\ndos solicitados,\n\nDios guarde a V.I.muchos anos\nMadrid, 8 de Enero de 1.982\n\nEL GENERAL CONSEJERO TOGADO INSTRUCTOR?\n\nJosé de Diego López 7\n\nINNO. SEÑOR, CORONEL DIRECTOR DEL CENTRO SUPERIOR DE INFORMACION DE LA DEFENSA\nC.E.S.I.D.- Paseo de la Castellana núm. 5.\nMADRID"
}